README.md
setup.py
cfn_sphere/__init__.py
cfn_sphere/cli.py
cfn_sphere/exceptions.py
cfn_sphere/file_generator.py
cfn_sphere/file_loader.py
cfn_sphere/util.py
cfn_sphere.egg-info/PKG-INFO
cfn_sphere.egg-info/SOURCES.txt
cfn_sphere.egg-info/dependency_links.txt
cfn_sphere.egg-info/entry_points.txt
cfn_sphere.egg-info/namespace_packages.txt
cfn_sphere.egg-info/requires.txt
cfn_sphere.egg-info/top_level.txt
cfn_sphere.egg-info/zip-safe
cfn_sphere/aws/__init__.py
cfn_sphere/aws/cfn.py
cfn_sphere/aws/ec2.py
cfn_sphere/aws/kms.py
cfn_sphere/aws/s3.py
cfn_sphere/aws/ssm.py
cfn_sphere/stack_configuration/__init__.py
cfn_sphere/stack_configuration/dependency_resolver.py
cfn_sphere/stack_configuration/parameter_resolver.py
cfn_sphere/template/__init__.py
cfn_sphere/template/template_handler.py
cfn_sphere/template/transformer.py
scripts/cf