Metadata-Version: 1.1
Name: cfn-sphere
Version: 1.0.4
Summary: cfn-sphere AWS CloudFormation management cli
Home-page: https://github.com/cfn-sphere/cfn-sphere
Author: Marco Hoyer
Author-email: marco_hoyer@gmx.de
License: APACHE LICENSE, VERSION 2.0
Platform: UNKNOWN
Classifier: Development Status :: 4 - Beta
Classifier: Environment :: Console
Classifier: Intended Audience :: Developers
Classifier: Intended Audience :: System Administrators
Classifier: License :: OSI Approved :: Apache Software License
Classifier: Programming Language :: Python
Classifier: Topic :: System :: Systems Administration
